Workbook

Sheet Assumptions
A1: 苹果公司 (AAPL) - 财务模型假设
A3: 收入增长率 (%)
A4: FY2020-FY2029 | B4: 增长率 | G4: 0.05 | H4: 0.06 | I4: 0.07 | J4: 0.06 | K4: 0.05
A6: 利润率假设 (%)
A7: 毛利率 | B7: 0.46
A8: 研发费用率 | B8: 0.07
A9: 销售及管理费用率 | B9: 0.06
A10: 有效税率 | B10: 0.15
A12: 营运资本假设 (天数)
A13: 应收账款周转天数 (DSO) | B13: 40
A14: 存货周转天数 (DIO) | B14: 10
A15: 应付账款周转天数 (DPO) | B15: 60
A17: 其他假设
A18: 资本支出占收入比例 | B18: 0.03
A19: 折旧占资本支出比例 | B19: 0.95
A20: 股利支付率 | B20: 0.15

Sheet IS
A1: 苹果公司 (AAPL) - 利润表
A2: 单位: 百万美元
B4: FY2020A | C4: FY2021A | D4: FY2022A | E4: FY2023A | F4: FY2024A | G4: FY2025E | H4: FY2026E | I4: FY2027E | J4: FY2028E | K4: FY2029E
A5: 收入 | B5: 274515 | C5: 365817 | D5: 394328 | E5: 383285 | F5: 383289 | G5: =F5*(1+Assumptions!G4) | H5: =G5*(1+Assumptions!H4) | I5: =H5*(1+Assumptions!I4) | J5: =I5*(1+Assumptions!J4) | K5: =J5*(1+Assumptions!K4)
A6: 营业成本 | B6: 169559 | C6: 212981 | D6: 223546 | E6: 214137 | F6: 210352 | G6: =G5*(1-Assumptions!$B$7) | H6: =H5*(1-Assumptions!$B$7) | I6: =I5*(1-Assumptions!$B$7) | J6: =J5*(1-Assumptions!$B$7) | K6: =K5*(1-Assumptions!$B$7)
A7: 毛利润 | B7: =B5-B6 | C7: =C5-C6 | D7: =D5-D6 | E7: =E5-E6 | F7: =F5-F6 | G7: =G5-G6 | H7: =H5-H6 | I7: =I5-I6 | ... K7: =K5-K6
A9: 研发费用 | B9: 18752 | C9: 21914 | D9: 26251 | E9: 29915 | F9: 31370 | G9: =G5*Assumptions!$B$8 | H9: =H5*Assumptions!$B$8 | I9: =I5*Assumptions!$B$8 | J9: =J5*Assumptions!$B$8 | K9: =K5*Assumptions!$B$8
A10: 销售及管理费用 | B10: 19916 | C10: 21914 | D10: 25094 | E10: 24932 | F10: 26097 | G10: =G5*Assumptions!$B$9 | H10: =H5*Assumptions!$B$9 | I10: =I5*Assumptions!$B$9 | J10: =J5*Assumptions!$B$9 | K10: =K5*Assumptions!$B$9
A11: 营业费用合计 | B11: =B9+B10 | C11: =C9+C10 | D11: =D9+D10 | E11: =E9+E10 | F11: =F9+F10 | G11: =G9+G10 | H11: =H9+H10 | I11: =I9+I10 | ... K11: =K9+K10
A13: 营业利润 | B13: =B7-B11 | C13: =C7-C11 | D13: =D7-D11 | E13: =E7-E11 | F13: =F7-F11 | G13: =G7-G11 | H13: =H7-H11 | I13: =I7-I11 | ... K13: =K7-K11
A15: 利息收入 | B15: 2444 | C15: 3543 | D15: 3810 | E15: 3762 | F15: 3762 | G15: =F15 | H15: =G15 | I15: =H15 | J15: =I15 | K15: =J15
A16: 利息费用 | B16: -2571 | C16: -2645 | D16: -2931 | E16: -3933 | F16: -3933 | G16: =F16 | H16: =G16 | I16: =H16 | J16: =I16 | K16: =J16
A17: 其他收入/(费用)
A18: 税前利润 | B18: =B13+B15+B16 | C18: =C13+C15+C16 | D18: =D13+D15+D16 | E18: =E13+E15+E16 | F18: =F13+F15+F16 | G18: =G13+G15+G16 | H18: =H13+H15+H16 | I18: =I13+I15+I16 | ... K18: =K13+K15+K16
A20: 所得税费用 | B20: =MAX(0,B18)*Assumptions!$B$10 | C20: =MAX(0,C18)*Assumptions!$B$10 | D20: =MAX(0,D18)*Assumptions!$B$10 | E20: =MAX(0,E18)*Assumptions!$B$10 | F20: =MAX(0,F18)*Assumptions!$B$10 | G20: =MAX(0,G18)*Assumptions!$B$10 | H20: =MAX(0,H18)*Assumptions!$B$10 | I20: =MAX(0,I18)*Assumptions!$B$10 | ... K20: =MAX(0,K18)*Assumptions!$B$10
A21: 净利润 | B21: =B18-B20 | C21: =C18-C20 | D21: =D18-D20 | E21: =E18-E20 | F21: =F18-F20 | G21: =G18-G20 | H21: =H18-H20 | I21: =I18-I20 | ... K21: =K18-K20
A23: 毛利率 (%) | B23: =B7/B5 | C23: =C7/C5 | D23: =D7/D5 | E23: =E7/E5 | F23: =F7/F5 | G23: =G7/G5 | H23: =H7/H5 | I23: =I7/I5 | ... K23: =K7/K5
A24: 营业利润率 (%) | B24: =B13/B5 | C24: =C13/C5 | D24: =D13/D5 | E24: =E13/E5 | F24: =F13/F5 | G24: =G13/G5 | H24: =H13/H5 | I24: =I13/I5 | ... K24: =K13/K5
A25: 净利润率 (%) | B25: =B21/B5 | C25: =C21/C5 | D25: =D21/D5 | E25: =E21/E5 | F25: =F21/F5 | G25: =G21/G5 | H25: =H21/H5 | I25: =I21/I5 | ... K25: =K21/K5

Sheet BS
A1: 苹果公司 (AAPL) - 资产负债表
A2: 单位: 百万美元
B4: FY2020A | C4: FY2021A | D4: FY2022A | E4: FY2023A | F4: FY2024A | G4: FY2025E | H4: FY2026E | I4: FY2027E | J4: FY2028E | K4: FY2029E
A5: 资产
A6: 流动资产
A7: 现金及现金等价物 | B7: 38016 | C7: 34940 | D7: 23646 | E7: 29965 | F7: 29965 | G7: =CF!G32 | H7: =CF!H32 | I7: =CF!I32 | J7: =CF!J32 | K7: =CF!K32
A8: 短期投资 | B8: 37368 | C8: 27699 | D8: 24658 | E8: 31587 | F8: 29135 | G8: =F8 | H8: =G8 | I8: =H8 | J8: =I8 | K8: =J8
A9: 应收账款净额 | B9: 16158 | C9: 26278 | D9: 28297 | E9: 29508 | F9: 30550 | G9: =Assumptions!$B$13*(IS!G5/365) | H9: =Assumptions!$B$13*(IS!H5/365) | I9: =Assumptions!$B$13*(IS!I5/365) | J9: =Assumptions!$B$13*(IS!J5/365) | K9: =Assumptions!$B$13*(IS!K5/365)
A10: 存货 | B10: 4061 | C10: 6580 | D10: 4946 | E10: 6331 | F10: 7200 | G10: =Assumptions!$B$14*(IS!G6/365) | H10: =Assumptions!$B$14*(IS!H6/365) | I10: =Assumptions!$B$14*(IS!I6/365) | J10: =Assumptions!$B$14*(IS!J6/365) | K10: =Assumptions!$B$14*(IS!K6/365)
A11: 其他流动资产 | B11: 32688 | C11: 35677 | D11: 37479 | E11: 40388 | F11: 42411 | G11: =F11 | H11: =G11 | I11: =H11 | J11: =I11 | K11: =J11
A12: 流动资产合计 | B12: =SUM(B7:B11) | C12: =SUM(C7:C11) | D12: =SUM(D7:D11) | E12: =SUM(E7:E11) | F12: =SUM(F7:F11) | G12: =SUM(G7:G11) | H12: =SUM(H7:H11) | I12: =SUM(I7:I11) | ... K12: =SUM(K7:K11)
A14: 非流动资产
A15: 长期投资 | B15: 100887 | C15: 127877 | D15: 120605 | E15: 100544 | F15: 94378 | G15: =F15 | H15: =G15 | I15: =H15 | J15: =I15 | K15: =J15
A16: 物业、厂房及设备净额 | B16: 36539 | C16: 39440 | D16: 42117 | E16: 43715 | F16: 45357 | G16: =F16 | H16: =G16 | I16: =H16 | J16: =I16 | K16: =J16
A17: 无形资产净额
A18: 其他非流动资产 | B18: 22283 | C18: 27979 | D18: 32172 | E18: 36423 | F18: 41307 | G18: =F18 | H18: =G18 | I18: =H18 | J18: =I18 | K18: =J18
A19: 非流动资产合计 | B19: =SUM(B15:B18) | C19: =SUM(C15:C18) | D19: =SUM(D15:D18) | E19: =SUM(E15:E18) | F19: =SUM(F15:F18) | G19: =SUM(G15:G18) | H19: =SUM(H15:H18) | I19: =SUM(I15:I18) | ... K19: =SUM(K15:K18)
A21: 资产总计 | B21: =B12+B19 | C21: =C12+C19 | D21: =D12+D19 | E21: =E12+E19 | F21: =F12+F19 | G21: =G12+G19 | H21: =H12+H19 | I21: =I12+I19 | ... K21: =K12+K19
A23: 负债及股东权益
A24: 流动负债
A25: 应付账款 | B25: 16377 | C25: 53730 | D25: 60039 | E25: 62833 | F25: 65844 | G25: =Assumptions!$B$15*(IS!G6/365) | H25: =Assumptions!$B$15*(IS!H6/365) | I25: =Assumptions!$B$15*(IS!I6/365) | J25: =Assumptions!$B$15*(IS!J6/365) | K25: =Assumptions!$B$15*(IS!K6/365)
A26: 应计费用
A27: 递延收入
A28: 短期债务
A29: 其他流动负债 | B29: 42967 | C29: 47763 | D29: 59279 | E29: 64845 | F29: 69031 | G29: =F29 | H29: =G29 | I29: =H29 | J29: =I29 | K29: =J29
A30: 流动负债合计 | B30: =SUM(B25:B29) | C30: =SUM(C25:C29) | D30: =SUM(D25:D29) | E30: =SUM(E25:E29) | F30: =SUM(F25:F29) | G30: =SUM(G25:G29) | H30: =SUM(H25:H29) | I30: =SUM(I25:I29) | ... K30: =SUM(K25:K29)
A32: 非流动负债
A33: 长期债务 | B33: 98661 | C33: 124719 | D33: 120069 | E33: 111088 | F33: 99028 | G33: =F33 | H33: =G33 | I33: =H33 | J33: =I33 | K33: =J33
A34: 递延所得税负债
A35: 其他非流动负债
A36: 非流动负债合计 | B36: =SUM(B33:B35) | C36: =SUM(C33:C35) | D36: =SUM(D33:D35) | E36: =SUM(E33:E35) | F36: =SUM(F33:F35) | G36: =SUM(G33:G35) | H36: =SUM(H33:H35) | I36: =SUM(I33:I35) | ... K36: =SUM(K33:K35)
A38: 负债合计 | B38: =B30+B36 | C38: =C30+C36 | D38: =D30+D36 | E38: =E30+E36 | F38: =F30+F36 | G38: =G30+G36 | H38: =H30+H36 | I38: =I30+I36 | ... K38: =K30+K36
A40: 股东权益
A41: 普通股 | B41: 50779 | C41: 57365 | D41: 64849 | E41: 73181 | F41: 83779
A42: 留存收益 | B42: 14933 | C42: 15157 | D42: -3068 | E42: -14050 | F42: -15545
A43: 累计其他综合收益
A44: 股东权益合计 | B44: =SUM(B41:B43) | C44: =SUM(C41:C43) | D44: =SUM(D41:D43) | E44: =SUM(E41:E43) | F44: =SUM(F41:F43) | G44: =SUM(G41:G43) | H44: =SUM(H41:H43) | I44: =SUM(I41:I43) | ... K44: =SUM(K41:K43)
A46: 负债及股东权益总计 | B46: =B38+B44 | C46: =C38+C44 | D46: =D38+D44 | E46: =E38+E44 | F46: =F38+F44 | G46: =G38+G44 | H46: =H38+H44 | I46: =I38+I44 | ... K46: =K38+K44

Sheet CF
A1: 苹果公司 (AAPL) - 现金流量表
A2: 单位: 百万美元
B4: FY2020A | C4: FY2021A | D4: FY2022A | E4: FY2023A | F4: FY2024A | G4: FY2025E | H4: FY2026E | I4: FY2027E | J4: FY2028E | K4: FY2029E
A5: 经营活动现金流
A6: 净利润 | B6: =IS!B21 | C6: =IS!C21 | D6: =IS!D21 | E6: =IS!E21 | F6: =IS!F21 | G6: =IS!G21 | H6: =IS!H21 | I6: =IS!I21 | ... K6: =IS!K21
A7: 折旧与摊销 | B7: 11056 | C7: 11105 | D7: 11112 | E7: 11544 | F7: 11283 | G7: =F7 | H7: =G7 | I7: =H7 | J7: =I7 | K7: =J7
A8: 股权激励费用 | B8: 6832 | C8: 9084 | D8: 9038 | E8: 10582 | F8: 11989 | G8: =F8 | H8: =G8 | I8: =H8 | J8: =I8 | K8: =J8
A9: 营运资本变动
A10: 应收账款变动 | C10: =-(C9-B9) | D10: =-(D9-C9) | E10: =-(E9-D9) | F10: =-(F9-E9) | G10: =-(G9-F9) | H10: =-(H9-G9) | I10: =-(I9-H9) | J10: =-(J9-I9) | K10: =-(K9-J9)
A11: 存货变动 | C11: =-(C10-B10) | D11: =-(D10-C10) | E11: =-(E10-D10) | F11: =-(F10-E10) | G11: =-(G10-F10) | H11: =-(H10-G10) | I11: =-(I10-H10) | J11: =-(J10-I10) | K11: =-(K10-J10)
A12: 应付账款变动 | C12: =C25-B25 | D12: =D25-C25 | E12: =E25-D25 | F12: =F25-E25 | G12: =G25-F25 | H12: =H25-G25 | I12: =I25-H25 | J12: =J25-I25 | K12: =K25-J25
A13: 其他经营性项目变动 | B13: 9722 | C13: 15908 | D13: 24724 | E13: 19200 | F13: 15620 | G13: =F13 | H13: =G13 | I13: =H13 | J13: =I13 | K13: =J13
A14: 经营活动现金流合计 | B14: =SUM(B6:B13) | C14: =SUM(C6:C13) | D14: =SUM(D6:D13) | E14: =SUM(E6:E13) | F14: =SUM(F6:F13) | G14: =SUM(G6:G13) | H14: =SUM(H6:H13) | I14: =SUM(I6:I13) | ... K14: =SUM(K6:K13)
A16: 投资活动现金流
A17: 资本支出 | B17: -7309 | C17: -11085 | D17: -10708 | E17: -10959 | F17: -9595 | G17: =-IS!G5*Assumptions!$B$21 | H17: =-IS!H5*Assumptions!$B$21 | I17: =-IS!I5*Assumptions!$B$21 | J17: =-IS!J5*Assumptions!$B$21 | K17: =-IS!K5*Assumptions!$B$21
A18: 收购支出
A19: 投资购买/(出售)
A20: 其他投资活动
A21: 投资活动现金流合计 | B21: =SUM(B17:B20) | C21: =SUM(C17:C20) | D21: =SUM(D17:D20) | E21: =SUM(E17:E20) | F21: =SUM(F17:F20) | G21: =SUM(G17:G20) | H21: =SUM(H17:H20) | I21: =SUM(I17:I20) | ... K21: =SUM(K17:K20)
A23: 筹资活动现金流
A24: 债务发行(偿还)
A25: 股权回购
A26: 股利支付
A27: 其他筹资活动
A28: 筹资活动现金流合计 | B28: =SUM(B24:B27) | C28: =SUM(C24:C27) | D28: =SUM(D24:D27) | E28: =SUM(E24:E27) | F28: =SUM(F24:F27) | G28: =SUM(G24:G27) | H28: =SUM(H24:H27) | I28: =SUM(I24:I27) | ... K28: =SUM(K24:K27)
A30: 现金变动净额 | B30: =B14+B21+B28 | C30: =C14+C21+C28 | D30: =D14+D21+D28 | E30: =E14+E21+E28 | F30: =F14+F21+F28 | G30: =G14+G21+G28 | H30: =H14+H21+H28 | I30: =I14+I21+I28 | ... K30: =K14+K21+K28
A31: 期初现金余额 | B31: 38016 | C31: =B32 | D31: =C32 | E31: =D32 | F31: =E32 | G31: =F32 | H31: =G32 | I31: =H32 | J31: =I32 | K31: =J32
A32: 期末现金余额 | B32: =B30+B31 | C32: =C30+C31 | D32: =D30+D31 | E32: =E30+E31 | F32: =F30+F31 | G32: =G30+G31 | H32: =H30+H31 | I32: =I30+I31 | ... K32: =K30+K31

Sheet Checks
A1: 模型验证检查
A3: 检查项目 | B3: FY2024A | C3: 状态 | D3: 说明
A4: 资产负债表平衡 | B4: =BS!F21-BS!F46 | C4: =IF(ABS(B4)<1,"✓ 通过","✗ 失败") | D4: 资产总计 = 负债及股东权益总计
A5: 现金验证 | B5: =CF!F32-BS!F7 | C5: =IF(ABS(B5)<1,"✓ 通过","✗ 失败") | D5: 现金流期末现金 = 资产负债表现金
A6: 净利润链接 | B6: =IS!F21-CF!F6 | C6: =IF(ABS(B6)<1,"✓ 通过","✗ 失败") | D6: 利润表净利润 = 现金流净利润
